flask_tokenauth.py
Flask_TokenAuth-0.1.0.dist-info/DESCRIPTION.rst
Flask_TokenAuth-0.1.0.dist-info/METADATA
Flask_TokenAuth-0.1.0.dist-info/RECORD
Flask_TokenAuth-0.1.0.dist-info/WHEEL
Flask_TokenAuth-0.1.0.dist-info/metadata.json
Flask_TokenAuth-0.1.0.dist-info/pbr.json
Flask_TokenAuth-0.1.0.dist-info/top_level.txt
